setup.py
Flask_Argonaut.egg-info/PKG-INFO
Flask_Argonaut.egg-info/SOURCES.txt
Flask_Argonaut.egg-info/dependency_links.txt
Flask_Argonaut.egg-info/not-zip-safe
Flask_Argonaut.egg-info/requires.txt
Flask_Argonaut.egg-info/top_level.txt
flask_argonaut/__init__.py