Metadata-Version: 1.1
Name: Flask-Argonaut
Version: 0.17
Summary: Flask extension use hashing data with Argon2
Home-page: UNKNOWN
Author: Anton Oleynik
Author-email: levantado@me.com
License: BSD
Download-URL: https://github.com/Levantado/Flask-Argonaut/tarball/v0.17
Platform: any
Classifier: Environment :: Web Environment
Classifier: Intended Audience :: Developers
Classifier: License :: OSI Approved :: BSD License
Classifier: Operating System :: OS Independent
Classifier: Programming Language :: Python :: 3.6
Classifier: Topic :: Internet :: WWW/HTTP :: Dynamic Content
Classifier: Topic :: Software Development :: Libraries :: Python Modules
